Metadata-Version: 2.4
Name: llama-index-packs-timescale-vector-autoretrieval
Version: 0.4.1
Summary: llama-index packs timescale_vector_autoretrieval integration
Author-email: Your Name <you@example.com>
Maintainer: cevian
License-Expression: MIT
License-File: LICENSE
Keywords: autoretrieval,index,timescale,vector
Requires-Python: <4.0,>=3.9
Requires-Dist: llama-index-core<0.15,>=0.13.0
Requires-Dist: llama-index-vector-stores-timescalevector<0.5,>=0.4.0
Requires-Dist: timescale-vector<0.0.5,>=0.0.4
